panoramix/__init__.py
panoramix/__main__.py
panoramix/abi.py
panoramix/contract.py
panoramix/decompiler.py
panoramix/folder.py
panoramix/function.py
panoramix/loader.py
panoramix/matcher.py
panoramix/postprocess.py
panoramix/prettify.py
panoramix/rewriter.py
panoramix/simplify.py
panoramix/sparser.py
panoramix/stack.py
panoramix/vm.py
panoramix/whiles.py
panoramix/core/__init__.py
panoramix/core/algebra.py
panoramix/core/arithmetic.py
panoramix/core/masks.py
panoramix/core/memloc.py
panoramix/core/variants.py
panoramix/data/supplement.db.xz
panoramix/utils/__init__.py
panoramix/utils/helpers.py
panoramix/utils/opcode_dict.py
panoramix/utils/signatures.py
panoramix/utils/supplement.py
panoramix_decompiler_abi-0.5.2.dist-info/LICENSE
panoramix_decompiler_abi-0.5.2.dist-info/METADATA
panoramix_decompiler_abi-0.5.2.dist-info/WHEEL
panoramix_decompiler_abi-0.5.2.dist-info/entry_points.txt
panoramix_decompiler_abi-0.5.2.dist-info/top_level.txt
panoramix_decompiler_abi-0.5.2.dist-info/RECORD
