Metadata-Version: 2.1
Name: panoramix-decompiler-abi
Version: 0.5.2
Summary: Decompiler at the heart of Eveem.org https://www.eveem.org/
Home-page: https://github.com/pkmelee337/panoramix
Author: Tomasz Kolinko / palkeo / Henk ter Harmsel
Author-email: henk@chaink.io
License: MIT
Keywords: ethereum evm decompiler Eveem.org
Platform: UNKNOWN
Classifier: Development Status :: 3 - Alpha
Classifier: Intended Audience :: Science/Research
Classifier: Topic :: Software Development :: Disassemblers
Classifier: Programming Language :: Python :: 3.8
Requires-Python: >3.8.0
License-File: LICENSE
Requires-Dist: coloredlogs
Requires-Dist: requests
Requires-Dist: web3
Requires-Dist: timeout-decorator
Requires-Dist: appdirs
